skql/__DecisionTreeClassifierAnalyzer.py
skql/__DecisionTreeClassifierConverter.py
skql/__init__.py
skql-0.0.2.dist-info/AUTHORS.rst
skql-0.0.2.dist-info/LICENSE
skql-0.0.2.dist-info/METADATA
skql-0.0.2.dist-info/WHEEL
skql-0.0.2.dist-info/top_level.txt
skql-0.0.2.dist-info/RECORD
