Metadata-Version: 2.1
Name: skql
Version: 0.0.2
Summary: Converts SKlearn python model objects into SQL query snippets.
Home-page: https://github.com/nullp00inter/skql
Author: Aditya Kumar
Author-email: adityakumar3008@gmail.com
License: MIT license
Keywords: skql
Platform: UNKNOWN
Classifier: Development Status :: 2 - Pre-Alpha
Classifier: Intended Audience :: Developers
Classifier: License :: OSI Approved :: MIT License
Classifier: Natural Language :: English
Classifier: Programming Language :: Python :: 3
Classifier: Programming Language :: Python :: 3.5
Classifier: Programming Language :: Python :: 3.6
Classifier: Programming Language :: Python :: 3.7
Classifier: Programming Language :: Python :: 3.8
Requires-Python: >=3.5
